benchmax/adapters/__init__.py
benchmax/adapters/verifiers/examples/verifiers_crm_example.py
benchmax/adapters/verifiers/examples/verifiers_excel_example.py
benchmax/adapters/verifiers/examples/verifiers_math_example.py
benchmax/adapters/verifiers/verifiers_adapters.py
benchmax/adapters/verl/benchmax_data_process.py
benchmax/adapters/verl/examples/config/benchmax_multiturn_grpo.yaml
benchmax/adapters/verl/examples/config/tool_config/benchmax_math_tool_config.yaml
benchmax/adapters/verl/examples/run_qwen2.5-3b_benchmax_math.sh
benchmax/envs/__init__.py
benchmax/envs/base_env.py
benchmax/envs/bounded_dict.py
benchmax/envs/crm/README.md
benchmax/envs/crm/crm_env.py
benchmax/envs/crm/salesforce_mcp.py
benchmax/envs/crm/salesforce_requirements.txt
benchmax/envs/excel/README.md
benchmax/envs/excel/data_utils.py
benchmax/envs/excel/excel_code_runner_mcp.py
benchmax/envs/excel/excel_env.py
benchmax/envs/excel/excel_utils.py
benchmax/envs/local_mcp_env.py
benchmax/envs/math/README.md
benchmax/envs/math/math_env.py
benchmax/envs/types.py
benchmax/envs/wikipedia/README.md
benchmax/envs/wikipedia/utils.py
benchmax/envs/wikipedia/wiki_env.py
benchmax/prompts/tools.py
benchmax-0.1.1.dist-info/LICENSE
benchmax-0.1.1.dist-info/METADATA
benchmax-0.1.1.dist-info/WHEEL
benchmax-0.1.1.dist-info/RECORD
