Metadata-Version: 2.3
Name: benchmax
Version: 0.1.1
Summary: Framework-Agnostic RL Environments for LLM Fine-Tuning
Author: cgft.io
Requires-Python: >=3.11,<3.13
Classifier: Programming Language :: Python :: 3
Classifier: Programming Language :: Python :: 3.11
Classifier: Programming Language :: Python :: 3.12
Provides-Extra: crm
Provides-Extra: excel
Provides-Extra: excel-linux
Provides-Extra: full
Provides-Extra: verifiers
Provides-Extra: verl
Provides-Extra: wikipedia
Requires-Dist: fastmcp (>=2.10.0,<2.11.0) ; extra == "excel-linux" or extra == "excel" or extra == "crm" or extra == "wikipedia" or extra == "full"
Requires-Dist: openpyxl (==3.1.5) ; extra == "excel-linux" or extra == "excel" or extra == "full"
Requires-Dist: python-dateutil (>=2.9.0,<2.10.0) ; extra == "crm" or extra == "full"
Requires-Dist: simple-salesforce (>=1.12.3) ; extra == "crm" or extra == "full"
Requires-Dist: verifiers[train] (>=0.1.1,<0.2.0) ; extra == "verifiers" or extra == "full"
Requires-Dist: verl (==0.5.0) ; extra == "verl" or extra == "full"
Requires-Dist: xlwings (==0.33.15) ; extra == "excel" or extra == "full"
